pyvclient/__init__.py
pyvclient/loadtest.py
pyvclient/pyvcli_akey.py
pyvclient/pyvcli_bigget.py
pyvclient/pyvcli_cd.py
pyvclient/pyvcli_cli.py
pyvclient/pyvcli_fdel.py
pyvclient/pyvcli_fget.py
pyvclient/pyvcli_file.py
pyvclient/pyvcli_fman.py
pyvclient/pyvcli_fput.py
pyvclient/pyvcli_gethelp.py
pyvclient/pyvcli_hello.py
pyvclient/pyvcli_id.py
pyvclient/pyvcli_ihost.py
pyvclient/pyvcli_login.py
pyvclient/pyvcli_ls.py
pyvclient/pyvcli_lsd.py
pyvclient/pyvcli_mkdir.py
pyvclient/pyvcli_pass.py
pyvclient/pyvcli_ping.py
pyvclient/pyvcli_qr.py
pyvclient/pyvcli_rabs.py
pyvclient/pyvcli_rcheck.py
pyvclient/pyvcli_rcount.py
pyvclient/pyvcli_rget.py
pyvclient/pyvcli_rlist.py
pyvclient/pyvcli_rman.py
pyvclient/pyvcli_rmdir.py
pyvclient/pyvcli_rput.py
pyvclient/pyvcli_sess.py
pyvclient/pyvcli_throt.py
pyvclient/pyvcli_uadd.py
pyvclient/pyvcli_uchpass.py
pyvclient/pyvcli_udel.py
pyvclient/pyvcli_uena.py
pyvclient/pyvcli_uini.py
pyvclient/pyvcli_uman.py
pyvclient/pyvcli_ver.py
pyvclient/docs/pyvcli_acc.html
pyvclient/docs/pyvcli_akey.html
pyvclient/docs/pyvcli_bigget.html
pyvclient/docs/pyvcli_cd.html
pyvclient/docs/pyvcli_cli.html
pyvclient/docs/pyvcli_fdel.html
pyvclient/docs/pyvcli_fget.html
pyvclient/docs/pyvcli_file.html
pyvclient/docs/pyvcli_fman.html
pyvclient/docs/pyvcli_fput.html
pyvclient/docs/pyvcli_gethelp.html
pyvclient/docs/pyvcli_hello.html
pyvclient/docs/pyvcli_id.html
pyvclient/docs/pyvcli_ihost.html
pyvclient/docs/pyvcli_login.html
pyvclient/docs/pyvcli_ls.html
pyvclient/docs/pyvcli_lsd.html
pyvclient/docs/pyvcli_mkdir.html
pyvclient/docs/pyvcli_pass.html
pyvclient/docs/pyvcli_ping.html
pyvclient/docs/pyvcli_qr.html
pyvclient/docs/pyvcli_rabs.html
pyvclient/docs/pyvcli_rcheck.html
pyvclient/docs/pyvcli_rcount.html
pyvclient/docs/pyvcli_replic.html
pyvclient/docs/pyvcli_rget.html
pyvclient/docs/pyvcli_rlist.html
pyvclient/docs/pyvcli_rman.html
pyvclient/docs/pyvcli_rmdir.html
pyvclient/docs/pyvcli_rput.html
pyvclient/docs/pyvcli_sess.html
pyvserv-1.1.0.dist-info/LICENSE
pyvserv-1.1.0.dist-info/METADATA
pyvserv-1.1.0.dist-info/WHEEL
pyvserv-1.1.0.dist-info/entry_points.txt
pyvserv-1.1.0.dist-info/top_level.txt
pyvserv-1.1.0.dist-info/RECORD
