Metadata-Version: 2.1
Name: pyvserv
Version: 1.1.0
Summary: High power secure server with blockchain backend.
Home-page: https://github.com/pglen/pyvserv
Author: Peter Glen
Author-email: peterglen99@gmail.com
Classifier: Programming Language :: Python :: 3
Classifier: License :: OSI Approved :: MIT License
Classifier: Operating System :: OS Independent
Requires-Python: >=3
License-File: LICENSE
Requires-Dist: pyvpacker
Requires-Dist: pydbase
Requires-Dist: pycryptodome
Requires-Dist: pyvecc
Requires-Dist: pyvguicom
Requires-Dist: playsound
